stactools/glad_glclu2020/__init__.py
stactools/glad_glclu2020/commands.py
stactools/glad_glclu2020/metadata.py
stactools/glad_glclu2020/stac.py
stactools/glad_glclu2020/data/annual_classes.csv
stactools/glad_glclu2020/data/change_classes.csv
stactools_glad_glclu2020-0.1.1.dist-info/LICENSE
stactools_glad_glclu2020-0.1.1.dist-info/METADATA
stactools_glad_glclu2020-0.1.1.dist-info/WHEEL
stactools_glad_glclu2020-0.1.1.dist-info/top_level.txt
stactools_glad_glclu2020-0.1.1.dist-info/RECORD
