Metadata-Version: 2.1
Name: stactools-glad-glclu2020
Version: 0.1.1
Summary: GLAD Land Use Land Cover 2020 stactools packages
Author-email: Henry Rodman <henry@developmentseed.org>
Maintainer-email: Henry Rodman <henry@developmentseed.org>
License: Apache-2.0
Project-URL: Github, https://github.com/stactools-packages/glad-glclu2020
Project-URL: Issues, https://github.com/stactools-packages/glad-glclu2020/issues
Keywords: stactools,pystac,catalog,STAC
Classifier: Development Status :: 3 - Alpha
Classifier: Intended Audience :: Developers
Classifier: License :: OSI Approved :: Apache Software License
Classifier: Natural Language :: English
Classifier: Programming Language :: Python :: 3
Classifier: Programming Language :: Python :: 3.10
Classifier: Programming Language :: Python :: 3.11
Classifier: Programming Language :: Python :: 3.12
Requires-Python: >=3.10
License-File: LICENSE
Requires-Dist: rasterio
Requires-Dist: parse>=1.20.2
Requires-Dist: pystac<2.0.0,>=1.11.0
Requires-Dist: python-slugify>=8.0.4
Requires-Dist: rio-cogeo>=5.3.6
Requires-Dist: rio-stac>=0.10.0
Requires-Dist: stactools>=0.5.0
Provides-Extra: dev
Requires-Dist: black~=24.4; extra == "dev"
Requires-Dist: codespell~=2.3; extra == "dev"
Requires-Dist: ipython>=8.29.0; extra == "dev"
Requires-Dist: jupyterlab>=4.3.0; extra == "dev"
Requires-Dist: mypy~=1.10; extra == "dev"
Requires-Dist: pre-commit~=4.0; extra == "dev"
Requires-Dist: pytest-cov~=6.0; extra == "dev"
Requires-Dist: pytest~=8.2; extra == "dev"
Requires-Dist: requests~=2.32; extra == "dev"
Requires-Dist: ruff==0.7.3; extra == "dev"
Provides-Extra: docs
Requires-Dist: pystac~=1.11; extra == "docs"
Requires-Dist: ipykernel~=6.29; extra == "docs"
Requires-Dist: jinja2~=3.1; extra == "docs"
